metadata_validator/__init__.py
metadata_validator/field_list.py
metadata_validator/filters.py
metadata_validator/forms.py
metadata_validator/main.py
metadata_validator/manage.py
metadata_validator/metadata_main.py
metadata_validator/mne.py
metadata_validator/models.py
metadata_validator/tables.py
metadata_validator/settings/__init__.py
metadata_validator/settings/settings.py
metadata_validator/settings/urls.py
metadata_validator/settings/wsgi.py
bilcheck-0.0.1.dist-info/METADATA
bilcheck-0.0.1.dist-info/WHEEL
bilcheck-0.0.1.dist-info/top_level.txt
bilcheck-0.0.1.dist-info/RECORD
