Metadata-Version: 2.1
Name: bilcheck
Version: 0.0.1
Summary: A package to check different sheets within a submission of a spreadsheet.
Home-page: UNKNOWN
Author: Keaton Hutchinson
Author-email: keatonhutchinson03@gmail.com
License: UNKNOWN
Keywords: python,bil
Platform: UNKNOWN
Classifier: Development Status :: 3 - Alpha
Classifier: Intended Audience :: Education
Classifier: Programming Language :: Python :: 2
Classifier: Programming Language :: Python :: 3
Classifier: Operating System :: MacOS :: MacOS X
Classifier: Operating System :: Microsoft :: Windows
Requires-Dist: pyexcel
Requires-Dist: xlrd
